mcp_python_temp/__init__.py
mcp_python_temp/cli.py
mcp_python_temp-0.1.1.dist-info/licenses/LICENSE
mcp_python_temp-0.1.1.dist-info/METADATA
mcp_python_temp-0.1.1.dist-info/WHEEL
mcp_python_temp-0.1.1.dist-info/entry_points.txt
mcp_python_temp-0.1.1.dist-info/top_level.txt
mcp_python_temp-0.1.1.dist-info/RECORD
