Metadata-Version: 2.4
Name: mcp-python-temp
Version: 0.1.1
Summary: Embedded Python MCP server for macOS tmp version
Author-email: korest75 <korest75@gmail.com>
License: MIT
Classifier: Programming Language :: Python :: 3
Classifier: License :: OSI Approved :: MIT License
Classifier: Operating System :: OS Independent
Requires-Python: >=3.9
License-File: LICENSE
Dynamic: license-file
